inspectorgadget/__init__.py
inspectorgadget-1.0.2.dist-info/LICENSE
inspectorgadget-1.0.2.dist-info/METADATA
inspectorgadget-1.0.2.dist-info/WHEEL
inspectorgadget-1.0.2.dist-info/RECORD
